odoo/addons/repair_restrict_lot/README.rst
odoo/addons/repair_restrict_lot/__init__.py
odoo/addons/repair_restrict_lot/__manifest__.py
odoo/addons/repair_restrict_lot/i18n/repair_restrict_lot.pot
odoo/addons/repair_restrict_lot/readme/CONTRIBUTORS.md
odoo/addons/repair_restrict_lot/readme/DESCRIPTION.md
odoo/addons/repair_restrict_lot/readme/USAGE.md
odoo/addons/repair_restrict_lot/static/description/icon.png
odoo/addons/repair_restrict_lot/static/description/index.html
odoo/addons/repair_restrict_lot/views/repair_order_view.xml
odoo_addon_repair_restrict_lot-17.0.1.0.0.2.dist-info/METADATA
odoo_addon_repair_restrict_lot-17.0.1.0.0.2.dist-info/WHEEL
odoo_addon_repair_restrict_lot-17.0.1.0.0.2.dist-info/top_level.txt
odoo_addon_repair_restrict_lot-17.0.1.0.0.2.dist-info/RECORD
